v3io/__init__.py
v3io/aio/dataplane/__init__.py
v3io/aio/dataplane/client.py
v3io/aio/dataplane/container.py
v3io/aio/dataplane/kv.py
v3io/aio/dataplane/kv_cursor.py
v3io/aio/dataplane/object.py
v3io/aio/dataplane/stream.py
v3io/aio/dataplane/transport/__init__.py
v3io/aio/dataplane/transport/aiohttp.py
v3io/common/__init__.py
v3io/common/helpers.py
v3io/dataplane/__init__.py
v3io/dataplane/batch.py
v3io/dataplane/client.py
v3io/dataplane/container.py
v3io/dataplane/kv.py
v3io/dataplane/kv_array.py
v3io/dataplane/kv_cursor.py
v3io/dataplane/kv_timestamp.py
v3io/dataplane/model.py
v3io/dataplane/object.py
v3io/dataplane/output.py
v3io/dataplane/request.py
v3io/dataplane/response.py
v3io/dataplane/stream.py
v3io/dataplane/transport/__init__.py
v3io/dataplane/transport/abstract.py
v3io/dataplane/transport/httpclient.py
v3io/dataplane/transport/requests.py
v3io/dataplane/transport/verifier.py
v3io/logger/__init__.py
v3io/logger/logger.py
v3io-0.7.2.dist-info/licenses/LICENSE
v3io-0.7.2.dist-info/METADATA
v3io-0.7.2.dist-info/WHEEL
v3io-0.7.2.dist-info/top_level.txt
v3io-0.7.2.dist-info/RECORD
